Metadata-Version: 1.0
Name: vin-distributions
Version: 0.1
Summary: Gaussian distributions
Home-page: UNKNOWN
Author: Vinit Kanse
Author-email: randomwave45@gmail.com
License: UNKNOWN
Platform: UNKNOWN
